rkm_codes/__init__.py
rkm_codes/rkm_codes.py
rkm_codes-1.0.dist-info/licenses/LICENSE
rkm_codes-1.0.dist-info/WHEEL
rkm_codes-1.0.dist-info/METADATA
rkm_codes-1.0.dist-info/RECORD
