Metadata-Version: 2.4
Name: rkm_codes
Version: 1.0
Summary: QuantiPhy support for RKM codes.
Keywords: quantiphy,rkm
Author: Ken Kundert
Author-email: rkm_codes@nurdletech.com
Requires-Python: >=3.6
Classifier: Development Status :: 5 - Production/Stable
Classifier: Intended Audience :: Developers
Classifier: License :: OSI Approved :: MIT License
Classifier: Natural Language :: English
Classifier: Operating System :: POSIX :: Linux
Classifier: Programming Language :: Python :: 3
Classifier: Topic :: Utilities
License-File: LICENSE
Requires-Dist: quantiphy>=2.4
Project-URL: changelog, https://emborg.readthedocs.io/en/latest/releases.html
Project-URL: repository, https://github.com/kenkundert/rkm_codes
